webstack_django_sorting/__init__.py
webstack_django_sorting/common.py
webstack_django_sorting/jinja2_globals.py
webstack_django_sorting/settings.py
webstack_django_sorting/templatetags/__init__.py
webstack_django_sorting/templatetags/sorting_tags.py
webstack_django_sorting-3.0.2.dist-info/METADATA
webstack_django_sorting-3.0.2.dist-info/WHEEL
webstack_django_sorting-3.0.2.dist-info/licenses/LICENSE.txt
webstack_django_sorting-3.0.2.dist-info/RECORD
