Metadata-Version: 2.3
Name: webstack-django-sorting
Version: 3.0.2
Summary: Easy sorting of tables with Django
Project-URL: repository, https://github.com/webstack/webstack-django-sorting.git
Project-URL: changelog, https://github.com/webstack/webstack-django-sorting/blob/master/CHANGELOG.md
Project-URL: Bug Tracker, https://github.com/webstack/webstack-django-sorting/issues
Author-email: "Karim A. (aka Directeur)" <directeur@gmail.com>, Eric Florenzano <floguy@gmail.com>, Stéphane Raimbault <stephane.raimbault@webstack.fr>, "S. Kossouho" <artscoop93@gmail.com>, "Joffrey M." <joffrey.mander@polyconseil.fr>
Maintainer-email: Stéphane Raimbault <stephane.raimbault@webstack.fr>
License-Expression: BSD-3-Clause
License-File: LICENSE.txt
Keywords: django,sorting,table
Classifier: Development Status :: 5 - Production/Stable
Classifier: Environment :: Web Environment
Classifier: Framework :: Django
Classifier: Intended Audience :: Developers
Classifier: License :: OSI Approved :: BSD License
Classifier: Natural Language :: English
Classifier: Operating System :: OS Independent
Classifier: Programming Language :: Python :: 3
Requires-Python: >=3.6
Requires-Dist: django<6.0,>=3.0
